Workbook
Name \A: #REF!
Name \A: #REF!
Name \A: #REF!
Name \A: #REF!
Name \d: #REF!
Name \d: #REF!
Name \d: #REF!
Name \d: #REF!
Name \Y: #REF!
Name \Y: #REF!
Name \Y: #REF!
Name \Z: #REF!
Name \Z: #REF!
Name \Z: #REF!
Name A: #REF!
Name A: #REF!
Name A: #REF!
Name B: #REF!
Name B: #REF!
Name B: #REF!
Name CAD: #REF!
Name CAD: #REF!
Name CAD: #REF!
Name CADY: #REF!
Name CADY: #REF!
Name CADY: #REF!
Name d: #REF!
Name d: #REF!
Name d: #REF!
Name DETAILS2PROCESS: #REF!
Name DETAILS2PROCESS: #REF!
Name DETAILS2PROCESS: #REF!
Name INV: #REF!
Name INV: #REF!
Name INV: #REF!
Name l: #REF!
Name l: #REF!
Name l: #REF!
Name ll: #REF!
Name ll: #REF!
Name ll: #REF!
Name newprintarea: #REF!
Name newprintarea: #REF!
Name newprintarea: #REF!
Name ODC: #REF!
Name ODC: #REF!
Name ODC: #REF!
Name Print_Area_MI: #REF!
Name Print_Area_MI: #REF!
Name Print_Area_MI: #REF!
Name PRINT_TITLES_MI: #REF!
Name PRINT_TITLES_MI: #REF!
Name PRINT_TITLES_MI: #REF!
Name RECE002_159255: #REF!
Name RECE002_159255: #REF!
Name RECE002_159255: #REF!
Name SUM: #REF!
Name SUM: #REF!
Name SUM: #REF!
Name TOTAL: #REF!

Sheet Sub Agreement Cover Page
A1: Aquatech Engineering, P.C.
A2: Subconsultant Agreement

Sheet Invoicing Instructions
A2: NYCDEP Invoicing Requirements
A4: Labor
A6: Invoice should show employee hours times direct labor salary
A7: Separate line for each the Overhead and Profit
A24: Timesheet backup must be provided to support direct labor hours billed, hours should be circled or highlighted.
A25: Principal's Time should not include profit, should bill Labor and overhead only
A26: Overtime must be approved in advance by NYCDEP
A27: For more detailed instruction please refer to Article XV - Cost plus payment terms
A30: Work Description Summary Report should accompany each invoice
A32: Other Direct Costs
A34: Mileage Reimbursement is governemnt standard per mile
A35: Receipts must be provided with personal travel expenses
... A42: Documents to be submitted
A43: 1 | B43: Invoice Summary
A44: 2 | B44: Task Detail
A45: 3 | B45: Timesheet Backup
A46: 4 | B46: Expense detail and supporting backup
A49: Invoices should be submitted on a monthly basis per contract requirement

Sheet Invoice Summary
B2: Place Company Letterhead Here
B4: Aquatech Engineering P.C.
B5: 15 Bonita Vista Road
B6: Mount Vernon, NY 10552
A9: Bill To:
A11: Melissa Carter, Project Manager | F11: Date: | G11: 02/23/26
A12: Stantec/Brown and Caldwell | F12: Invoice #: | G12: SBCAQ0005
A13: 475 Fifth Avenue, 12th Floor, New York, NY 10017
B16: Contract ID: BWT Citywide Regulatory Program Assistance, 1539-REG
B17: Contract Reg No.: Assignment 014 (ASGMT-014)
B20: Support Services for the Period: | C20: 45680 | D20: To | E20: 46072
B22: This Invoice | D22: =D34 -> 12201.21
H23: % Complete
C24: Total Billed | D24: This | E24: Total Billed | F24: Task Order | G24: Balance | H24: This | I24: To
A25: Contract Summary by Task | C25: Previously | D25: Invoice | E25: to Date | F25: Maximum | G25: Remaining | H25: Payment | I25: Date
A26: Task
A27: 3 | B27: CONSENT ORDER AND PERMIT COMPLIANCE TECHNICAL SUPPORT | C27: =C28+C29 -> 115308.98 | D27: ='Invoice Template_Task# 5'!N38 -> 12201.21 | E27: =C27+D27 -> 127510.19 | F27: =SUM(F28:F31) -> 211525.17 | G27: =F27-E27 -> 84014.98 | H27: =D27/F27 -> 0.057682072 | I27: =(E27/F27) -> 0.60281332
B28: 3.1 - Characterize Existing Conditions | C28: =Prior!B12 -> 59019.06 | D28: 0 | E28: =C28 -> 59019.06 | F28: 62430.1 | G28: =F28-E28 -> 3411.04 | H28: =D28/F28 -> 0 | I28: =(E28/F28) -> 0.94536225
B29: 3.2 - Jamaica Bay Beneficial Use | C29: =Prior!C12 -> 56289.92 | D29: ='Invoice Template_Task# 5'!N21+'Invoice Template_Task# 5'!N28 -> 12201.21 | E29: =D29+C29 -> 68491.13 | F29: 75118.07 | G29: =F29-E29 -> 6626.94 | H29: =D29/F29 -> 0.1624271 | I29: =(E29/F29) -> 0.91177968
B30: 3.4 - Variance Recommendations | C30: 0 | D30: 0 | E30: 0 | F30: 64614.55 | G30: =F30-E30 -> 64614.55 | H30: =D30/F30 -> 0 | I30: =(E30/F30) -> 0
B31: 3.5 - Meetings with DEC | C31: 0 | D31: 0 | E31: 0 | F31: 9362.45 | G31: =F31-E31 -> 9362.45 | H31: =D31/F31 -> 0 | I31: =(E31/F31) -> 0
B34: Total Contract | C34: =C28+C29 -> 115308.98 | D34: =D29+D28 -> 12201.21 | E34: =SUM(E28:E29) -> 127510.19 | F34: =SUM(F28:F31) -> 211525.17 | G34: =SUM(G28:G33) -> 84014.98 | H34: =H27 -> 0.057682072 | I34: =I27 -> 0.60281332
F41: Authorized Signature | I41: Title

Sheet Prior
A5: Prior
A6: 45931 | B6: 27326.73
A7: 45962 | B7: 31692.33
A8: 45992 | C8: 35550.75
A9: 46023 | C9: 20739.17
A10: 46054
A11: 46082
A12: Total | B12: =SUM(B5:B11) -> 59019.06 | C12: =SUM(C5:C11) -> 56289.92

Sheet Supporting Docs Cover Page
A1: Aquatech Engineering
A2: Supporting Documentation

Sheet Invoice Template_Task# 5
A1: ='Invoice Summary'!B1 -> 0
N3: Invoice
I5: Invoice No. | N5: ='Invoice Summary'!G12 -> SBCAQ0005
I6: Invoice Date | N6: ='Invoice Summary'!G11 -> 02/23/26
A8: Professional Services and Expense Detail
A10: ='Invoice Summary'!B27 -> CONSENT ORDER AND PERMIT COMPLIANCE TECHNICAL SUPPORT
A11: Task 3.2 - Jamaica Bay Beneficial Use
A12: Employee Name | D12: Title | H12: Hours | L12: Direct Salary Rate | N12: Amount
A13: STAFF
A14: Zachary | B14: Gilliam | D14: Data Analyst | H14: 0 | L14: 52.26 | N14: =ROUND(H14*L14,2) -> 0
A15: Stacey | B15: Hodge | D15: Engineer | H15: 0 | L15: 51.64 | N15: =ROUND(H15*L15,2) -> 0
A16: Ailsa | B16: Welch | D16: Project Manager/Data Analyst | H16: 16 | L16: 75 | N16: =ROUND(H16*L16,2) -> 1200
A17: Robert | B17: Svadlenka | D17: Senior Engineer | H17: 10 | L17: 61.5 | N17: =ROUND(H17*L17,2) -> 615
H18: =SUM(H13:H17) -> 26 | N18: =SUM(N13:N17) -> 1815
L19: Overhead Rate @114% | N19: =ROUND(N18*1.14,2) -> 2069.1
L20: Profit @ 10% on Labor & OH | N20: =ROUND((N18+N19)*0.1,2) -> 388.41
J21: Direct Labor | N21: =SUM(N18:N20) -> 4272.51
A22: Employee Name | D22: Title | H22: Hours | L22: Billing Rate | N22: Amount
A23: Bertrand | B23: Byrne | D23: Chief Engineer/Principal | H23: 38 | L23: 97.5 | N23: =ROUND(H23*L23,2) -> 3705
N24: =ROUND(H24*L24,2) -> 0
H25: =SUM(H23:H24) -> 38 | N25: =SUM(N23:N24) -> 3705
L26: Overhead Rate @114% | N26: =ROUND(N25*1.14,2) -> 4223.7
L27: Profit @ 0% on Labor & OH | N27: =ROUND((N25+N26)*0,2) -> 0
J28: Direct Labor | N28: =SUM(N25:N27) -> 7928.7
J30: Total Labor | N30: =N28+N21 -> 12201.21
A32: Expense Detail
J35: Direct Expenses | N35: =SUM(N33:N34) -> 0
J38: Total Task 3 | N38: =N35+N30 -> 12201.21

Sheet Timesheet Backup
B8: Timesheet BackUp

Sheet Sheet2
